nossl/__init__.py
nossl-0.0.2.dist-info/METADATA
nossl-0.0.2.dist-info/WHEEL
nossl-0.0.2.dist-info/entry_points.txt
nossl-0.0.2.dist-info/top_level.txt
nossl-0.0.2.dist-info/RECORD
