Metadata-Version: 2.1
Name: nossl
Version: 0.0.2
Summary: Change default behavior of ssl and requests library
Home-page: UNKNOWN
Author: Sangwon Lee
Author-email: lsw91.main@gmail.com
License: MIT
Platform: UNKNOWN
Requires-Python: >=3.6
Requires-Dist: requests
